face_recognition/__init__.py
face_recognition/api.py
face_recognition/face_detection_cli.py
face_recognition/face_recognition_cli.py
face_recognition-1.2.2.dist-info/DESCRIPTION.rst
face_recognition-1.2.2.dist-info/METADATA
face_recognition-1.2.2.dist-info/RECORD
face_recognition-1.2.2.dist-info/WHEEL
face_recognition-1.2.2.dist-info/entry_points.txt
face_recognition-1.2.2.dist-info/metadata.json
face_recognition-1.2.2.dist-info/top_level.txt
