Metadata-Version: 1.1
Name: face_recognition
Version: 1.2.2
Summary: Recognize faces from Python or from the command line
Home-page: https://github.com/ageitgey/face_recognition
Author: Adam Geitgey
Author-email: ageitgey@gmail.com
License: MIT license
Keywords: face_recognition
Platform: UNKNOWN
Classifier: Development Status :: 4 - Beta
Classifier: Intended Audience :: Developers
Classifier: License :: OSI Approved :: MIT License
Classifier: Natural Language :: English
Classifier: Programming Language :: Python :: 2
Classifier: Programming Language :: Python :: 2.6
Classifier: Programming Language :: Python :: 2.7
Classifier: Programming Language :: Python :: 3
Classifier: Programming Language :: Python :: 3.3
Classifier: Programming Language :: Python :: 3.4
Classifier: Programming Language :: Python :: 3.5
Classifier: Programming Language :: Python :: 3.6
